Velra/__init__.py
Velra/core.py
Velra/errorhandling.py
Velra/loader.py
Velra/main.py
velra-0.2.8.dist-info/licenses/LICENSE
velra-0.2.8.dist-info/METADATA
velra-0.2.8.dist-info/WHEEL
velra-0.2.8.dist-info/top_level.txt
velra-0.2.8.dist-info/RECORD
